mp_manager/__init__.py
mp_manager/base_handler.py
mp_manager/manager.py
mp_manager/process_helpers.py
mp_manager/utils.py
mp_manager-0.2.dist-info/COPYING
mp_manager-0.2.dist-info/METADATA
mp_manager-0.2.dist-info/WHEEL
mp_manager-0.2.dist-info/top_level.txt
mp_manager-0.2.dist-info/RECORD
