Metadata-Version: 2.1
Name: mp-manager
Version: 0.2
Summary: Simple python multiprocessing manager
Home-page: https://github.com/dmiwell/mp_manager
Author: Dmitriy Pomazunovskiy
Author-email: forestwheel@gmail.com
License: BSD
Platform: UNKNOWN
Classifier: Development Status :: 5 - Production/Stable
Classifier: Intended Audience :: Developers
Classifier: License :: OSI Approved :: BSD License
Classifier: Programming Language :: Python
Classifier: Programming Language :: Python :: 3.7
Classifier: Topic :: Software Development
